{
  "dungeon_grid": {
    "type": "array",
    "orientation": "vertical",
    "content": [
      {
        "type": "array",
        "orientation": "horizontal",
        "margin": "5,0",
        "content": [
          {
            "type": "canvas",
            "width": 32,
            "height": 32,
            "margin": "1,2",
            "content": [
              {
                "type": "item",
                "item": "skyview_label",
                "canvas_depth": 1,
                "width": 32,
                "height": 12
              },
              {
                "type": "item",
                "item": "skyviewsk",
                "canvas_depth": 1,
                "canvas_left": 0,
                "canvas_top": 16,
                "width": 16,
                "height": 16
              },
              {
                "type": "item",
                "item": "skyviewbk",
                "canvas_depth": 1,
                "canvas_left": 16,
                "canvas_top": 16,
                "width": 16,
                "height": 16
              }
            ]
          },
          {
            "type": "canvas",
            "width": 32,
            "height": 32,
            "margin": "1,2",
            "content": [
              {
                "type": "item",
                "item": "earth_label",
                "canvas_depth": 1,
                "width": 32,
                "height": 12
              },
              {
                "type": "item",
                "item": "earthbk",
                "canvas_depth": 1,
                "canvas_left": 16,
                "canvas_top": 16,
                "width": 16,
                "height": 16
              }
            ]
          },
          {
            "type": "canvas",
            "width": 32,
            "height": 32,
            "margin": "1,2",
            "content": [
              {
                "type": "item",
                "item": "mine_label",
                "canvas_depth": 1,
                "width": 32,
                "height": 12
              },
              {
                "type": "item",
                "item": "minesk",
                "canvas_depth": 1,
                "canvas_left": 0,
                "canvas_top": 16,
                "width": 16,
                "height": 16
              },
              {
                "type": "item",
                "item": "minebk",
                "canvas_depth": 1,
                "canvas_left": 16,
                "canvas_top": 16,
                "width": 16,
                "height": 16
              }
            ]
          },
          {
            "type": "canvas",
            "width": 32,
            "height": 32,
            "margin": "1,2",
            "content": [
              {
                "type": "item",
                "item": "cistern_label",
                "canvas_depth": 1,
                "width": 32,
                "height": 12
              },
              {
                "type": "item",
                "item": "cisternsk",
                "canvas_depth": 1,
                "canvas_left": 0,
                "canvas_top": 16,
                "width": 16,
                "height": 16
              },
              {
                "type": "item",
                "item": "cisternbk",
                "canvas_depth": 1,
                "canvas_left": 16,
                "canvas_top": 16,
                "width": 16,
                "height": 16
              }
            ]
          },
          {
            "type": "canvas",
            "width": 32,
            "height": 32,
            "margin": "1,2",
            "content": [
              {
                "type": "item",
                "item": "sandship_label",
                "canvas_depth": 1,
                "width": 32,
                "height": 12
              },
              {
                "type": "item",
                "item": "sandshipsk",
                "canvas_depth": 1,
                "canvas_left": 0,
                "canvas_top": 16,
                "width": 16,
                "height": 16
              },
              {
                "type": "item",
                "item": "sandshipbk",
                "canvas_depth": 1,
                "canvas_left": 16,
                "canvas_top": 16,
                "width": 16,
                "height": 16
              }
            ]
          },
          {
            "type": "canvas",
            "width": 32,
            "height": 32,
            "margin": "1,2",
            "content": [
              {
                "type": "item",
                "item": "sanc_label",
                "canvas_depth": 1,
                "width": 32,
                "height": 12
              },
              {
                "type": "item",
                "item": "sancsk",
                "canvas_depth": 1,
                "canvas_left": 0,
                "canvas_top": 16,
                "width": 16,
                "height": 16
              },
              {
                "type": "item",
                "item": "sancbk",
                "canvas_depth": 1,
                "canvas_left": 16,
                "canvas_top": 16,
                "width": 16,
                "height": 16
              }
            ]
          },
          {
            "type": "canvas",
            "width": 32,
            "height": 32,
            "margin": "1,2",
            "content": [
              {
                "type": "item",
                "item": "skykeep_label",
                "canvas_depth": 1,
                "width": 32,
                "height": 12
              },
              {
                "type": "item",
                "item": "skykeepsk",
                "canvas_depth": 1,
                "canvas_left": 0,
                "canvas_top": 16,
                "width": 16,
                "height": 16
              },
              {
                "type": "item",
                "item": "tri",
                "canvas_depth": 1,
                "canvas_left": 16,
                "canvas_top": 16,
                "width": 16,
                "height": 16
              }
            ]
          },
          {
            "type": "canvas",
            "width": 32,
            "height": 32,
            "margin": "1,2",
            "content": [
              {
                "type": "item",
                "item": "cave_label",
                "canvas_depth": 1,
                "width": 32,
                "height": 12
              },
              {
                "type": "item",
                "item": "cavesk",
                "canvas_depth": 1,
                "canvas_left": 0,
                "canvas_top": 16,
                "width": 16,
                "height": 16
              }
            ]
          }
        ]
      }
    ]
  }
}